svhet/__init__.py
svhet/cli.py
svhet/const.py
svhet/evidence.py
svhet/filtering.py
svhet/read_sets.py
svhet/reads.py
svhet/sv.py
svhet/variants.py
svhet/__pycache__/__init__.cpython-312.pyc
svhet/__pycache__/cli.cpython-312.pyc
svhet/__pycache__/const.cpython-312.pyc
svhet/__pycache__/evidence.cpython-312.pyc
svhet/__pycache__/filtering.cpython-312.pyc
svhet/__pycache__/read_sets.cpython-312.pyc
svhet/__pycache__/reads.cpython-312.pyc
svhet/__pycache__/sv.cpython-312.pyc
svhet/__pycache__/variants.cpython-312.pyc
svhet/utils/__init__.py
svhet/utils/bam.py
svhet/utils/log.py
svhet/utils/misc.py
svhet/utils/__pycache__/__init__.cpython-312.pyc
svhet/utils/__pycache__/bam.cpython-312.pyc
svhet/utils/__pycache__/log.cpython-312.pyc
svhet/utils/__pycache__/misc.cpython-312.pyc
svhet-0.1.1.dist-info/licenses/LICENSE
svhet-0.1.1.dist-info/METADATA
svhet-0.1.1.dist-info/WHEEL
svhet-0.1.1.dist-info/entry_points.txt
svhet-0.1.1.dist-info/top_level.txt
svhet-0.1.1.dist-info/RECORD
