Metadata-Version: 2.4
Name: svhet
Version: 0.1.1
Summary: An accurate NGS-based structural variant detection tool for human genomes
Home-page: https://github.com/snakesch/svhet
Author: Louis She
Author-email: Louis She <snakesch@connect.hku.hk>
License: MIT License
Project-URL: Repository, https://github.com/snakesch/SVhet
Project-URL: Issues, https://github.com/snakesch/SVhet/issues
Keywords: genomics,structural variants,variant detection
Requires-Python: >=3.11
License-File: LICENSE
Requires-Dist: cyvcf2>=0.31.0
Requires-Dist: pysam>=0.23.0
Requires-Dist: pybedtools>=0.12.0
Requires-Dist: tqdm>=4.67.1
Requires-Dist: numpy<2,>=1.26.4
Dynamic: author
Dynamic: home-page
Dynamic: license-file
Dynamic: requires-python
